setup.py
docs/conf.py
pytradier/__init__.py
pytradier/base.py
pytradier/const.py
pytradier/exceptions.py
pytradier/tradier.py
pytradier/account/__init__.py
pytradier/account/account.py
pytradier/account/balance.py
pytradier/account/costbasis.py
pytradier/account/events.py
pytradier/account/history.py
pytradier/account/order.py
pytradier/account/orderstatus.py
pytradier/account/position.py
pytradier/company/__init__.py
pytradier/company/action.py
pytradier/company/calendar.py
pytradier/company/chain.py
pytradier/company/company.py
pytradier/company/dividend.py
pytradier/company/expirations.py
pytradier/company/history.py
pytradier/company/info.py
pytradier/company/ratio.py
pytradier/company/report.py
pytradier/company/stats.py
pytradier/company/timesales.py
pytradier/market/__init__.py
pytradier/market/calendar.py
pytradier/market/lookup.py
pytradier/market/market.py
pytradier/market/search.py
pytradier/market/status.py
pytradier/order/__init__.py
pytradier/order/order.py
pytradier/securities/__init__.py
pytradier/securities/option.py
pytradier/securities/quote.py
pytradier/securities/stock.py
pytradier/user/__init__.py
pytradier/user/balances.py
pytradier/user/cost_basis.py
pytradier/user/history.py
pytradier/user/orders.py
pytradier/user/positions.py
pytradier/user/profile.py
pytradier_collegroup-1.0.0.dist-info/METADATA
pytradier_collegroup-1.0.0.dist-info/WHEEL
pytradier_collegroup-1.0.0.dist-info/licenses/LICENSE
pytradier_collegroup-1.0.0.dist-info/RECORD
