Metadata-Version: 2.1
Name: PyTradier_collegroup
Version: 1.0.0
Summary: PyTradier moved to PyPi
Author-email: arthurcolle <arthur@collegroup.com>
License-File: LICENSE
Classifier: License :: OSI Approved :: MIT License
Classifier: Operating System :: OS Independent
Classifier: Programming Language :: Python :: 3
Requires-Python: >=3.7
